pipdate/__about__.py
pipdate/__init__.py
pipdate/__main__.py
pipdate/main.py
pipdate/update.py
pipdate-0.5.6.dist-info/LICENSE
pipdate-0.5.6.dist-info/METADATA
pipdate-0.5.6.dist-info/WHEEL
pipdate-0.5.6.dist-info/entry_points.txt
pipdate-0.5.6.dist-info/top_level.txt
pipdate-0.5.6.dist-info/RECORD
